katuyou/__init__.py
katuyou/conjugations.py
katuyou-0.1.dist-info/METADATA
katuyou-0.1.dist-info/WHEEL
katuyou-0.1.dist-info/top_level.txt
katuyou-0.1.dist-info/RECORD
