Metadata-Version: 2.1
Name: katuyou
Version: 0.1
Summary: Conjugates verbs and i-adjectives according to 8 helping verbs (た、せる、たい、ない、う、て、ます、だ）
Author: Lachlan M.
Author-email: azure.fjord.ao@gmail.com
